django_tus/__init__.py
django_tus/apps.py
django_tus/conf.py
django_tus/errors.py
django_tus/response.py
django_tus/signals.py
django_tus/tus_server.py
django_tus/tusfile.py
django_tus/urls.py
django_tus/views.py
django_tus-0.5.0.dist-info/AUTHORS.rst
django_tus-0.5.0.dist-info/LICENSE
django_tus-0.5.0.dist-info/METADATA
django_tus-0.5.0.dist-info/WHEEL
django_tus-0.5.0.dist-info/top_level.txt
django_tus-0.5.0.dist-info/RECORD
