Metadata-Version: 2.1
Name: django-tus
Version: 0.5.0
Summary: Django app implementing server side of tus v1.0.0 powering resumable file uploads for django projects
Home-page: https://github.com/alican/django-tus
Author: Alican Toprak
Author-email: alican@querhin.com
License: MIT
Keywords: django-tus
Platform: UNKNOWN
Classifier: Development Status :: 5 - Production/Stable
Classifier: Framework :: Django
Classifier: Framework :: Django :: 2.2
Classifier: Framework :: Django :: 3.0
Classifier: Framework :: Django :: 3.1
Classifier: Intended Audience :: Developers
Classifier: License :: OSI Approved :: BSD License
Classifier: Natural Language :: English
Classifier: Operating System :: OS Independent
Classifier: Programming Language :: Python :: 3.5
Classifier: Programming Language :: Python :: 3.6
Classifier: Programming Language :: Python :: 3.7
Classifier: Programming Language :: Python :: 3.8
Classifier: Topic :: Internet :: WWW/HTTP
Requires-Python: >=3.5
Requires-Dist: django (>=2.2)
Requires-Dist: django-appconf
Requires-Dist: pathvalidate (==2.3.0)
